.gitignore
LICENSE
LICENSE.txt
README.md
pyproject.toml
setup.cfg
setup.py
.idea/.gitignore
.idea/misc.xml
.idea/modules.xml
.idea/py-handling-response.iml
.idea/vcs.xml
.idea/inspectionProfiles/Project_Default.xml
.idea/inspectionProfiles/profiles_settings.xml
src/handlingresponse/__init__.py
src/handlingresponse/main.py
src/handlingresponse/example/__init__.py
src/handlingresponse/example/example.py
src/py_handling_response.egg-info/PKG-INFO
src/py_handling_response.egg-info/SOURCES.txt
src/py_handling_response.egg-info/dependency_links.txt
src/py_handling_response.egg-info/requires.txt
src/py_handling_response.egg-info/top_level.txt